{"expireTime":9007200897367436000,"key":"gatsby-plugin-mdx-entire-payload-ee97c8e2c041cc84a6e9f787194f7167-","val":{"mdast":{"type":"root","children":[{"type":"paragraph","children":[{"type":"text","value":"To protect specific endpoints from being overwhelmed by traffic spikes, ","position":{"start":{"line":1,"column":1,"offset":0},"end":{"line":1,"column":73,"offset":72},"indent":[]}},{"type":"link","title":null,"url":"https://developers.cloudflare.com/waiting-room/about","children":[{"type":"text","value":"set up a waiting room","position":{"start":{"line":1,"column":74,"offset":73},"end":{"line":1,"column":95,"offset":94},"indent":[]}}],"position":{"start":{"line":1,"column":73,"offset":72},"end":{"line":1,"column":150,"offset":149},"indent":[]}},{"type":"text","value":".","position":{"start":{"line":1,"column":150,"offset":149},"end":{"line":1,"column":151,"offset":150},"indent":[]}}],"position":{"start":{"line":1,"column":1,"offset":0},"end":{"line":1,"column":151,"offset":150},"indent":[]}},{"type":"export","value":"export const _frontmatter = {}","position":{"start":{"line":3,"column":1,"offset":152},"end":{"line":3,"column":31,"offset":182},"indent":[]}}],"position":{"start":{"line":1,"column":1,"offset":0},"end":{"line":3,"column":31,"offset":182}}},"scopeImports":[],"scopeIdentifiers":[],"rawMDXOutput":"/* @jsx mdx */\nimport { mdx } from '@mdx-js/react';\n/* @jsx mdx */\n\nexport const _frontmatter = {};\nconst makeShortcode = name => function MDXDefaultShortcode(props) {\n  console.warn(\"Component \" + name + \" was not imported, exported, or provided by MDXProvider as global scope\")\n  return <div {...props}/>\n};\n\nconst layoutProps = {\n  _frontmatter\n};\nconst MDXLayout = \"wrapper\"\nexport default function MDXContent({\n  components,\n  ...props\n}) {\n  return <MDXLayout {...layoutProps} {...props} components={components} mdxType=\"MDXLayout\">\n    <p>{`To protect specific endpoints from being overwhelmed by traffic spikes, `}<a parentName=\"p\" {...{\n        \"href\": \"https://developers.cloudflare.com/waiting-room/about\"\n      }}>{`set up a waiting room`}</a>{`.`}</p>\n\n    </MDXLayout>;\n}\n\n;\nMDXContent.isMDXComponent = true;"}}