{"data":{"mdx":{"id":"4d75828d-266c-5f54-b891-aa02c3a0171e","body":"var _excluded = [\"components\"];\n\nfunction _extends() { _extends = Object.assign || function (target) { for (var i = 1; i < arguments.length; i++) { var source = arguments[i]; for (var key in source) { if (Object.prototype.hasOwnProperty.call(source, key)) { target[key] = source[key]; } } } return target; }; return _extends.apply(this, arguments); }\n\nfunction _objectWithoutProperties(source, excluded) { if (source == null) return {}; var target = _objectWithoutPropertiesLoose(source, excluded); var key, i; if (Object.getOwnPropertySymbols) { var sourceSymbolKeys = Object.getOwnPropertySymbols(source); for (i = 0; i < sourceSymbolKeys.length; i++) { key = sourceSymbolKeys[i]; if (excluded.indexOf(key) >= 0) continue; if (!Object.prototype.propertyIsEnumerable.call(source, key)) continue; target[key] = source[key]; } } return target; }\n\nfunction _objectWithoutPropertiesLoose(source, excluded) { if (source == null) return {}; var target = {}; var sourceKeys = Object.keys(source); var key, i; for (i = 0; i < sourceKeys.length; i++) { key = sourceKeys[i]; if (excluded.indexOf(key) >= 0) continue; target[key] = source[key]; } return target; }\n\n/* @jsx mdx */\nvar _frontmatter = {\n  \"pcx-content-type\": \"reference\",\n  \"order\": 450\n};\n\nvar makeShortcode = function makeShortcode(name) {\n  return function MDXDefaultShortcode(props) {\n    console.warn(\"Component \" + name + \" was not imported, exported, or provided by MDXProvider as global scope\");\n    return mdx(\"div\", props);\n  };\n};\n\nvar TableWrap = makeShortcode(\"TableWrap\");\nvar Type = makeShortcode(\"Type\");\nvar layoutProps = {\n  _frontmatter: _frontmatter\n};\nvar MDXLayout = \"wrapper\";\nreturn function MDXContent(_ref) {\n  var components = _ref.components,\n      props = _objectWithoutProperties(_ref, _excluded);\n\n  return mdx(MDXLayout, _extends({}, layoutProps, props, {\n    components: components,\n    mdxType: \"MDXLayout\"\n  }), mdx(\"h1\", {\n    \"id\": \"json-object\"\n  }, \"JSON object\"), mdx(\"h2\", {\n    \"id\": \"filters-object-structure-and-properties\"\n  }, \"Filters object structure and properties\"), mdx(\"p\", null, \"A JSON response for the \", mdx(\"a\", {\n    parentName: \"p\",\n    \"href\": \"https://api.cloudflare.com/#filters-properties\"\n  }, \"Filters API\"), \" has this structure:\"), mdx(\"pre\", null, mdx(\"code\", {\n    parentName: \"pre\",\n    \"className\": \"language-json\"\n  }, \"{\\n  \\\"id\\\": \\\"6f58318e7fa2477a23112e8118c66f61\\\",\\n  \\\"expression\\\": \\\"http.request.uri.path ~ \\\\\\\"^.*/wp-login.php$\\\\\\\" or http.request.uri.path ~ \\\\\\\"^.*/xmlrpc.php$\\\\\\\"\\\",\\n  \\\"paused\\\": true,\\n  \\\"description\\\": \\\"WordPress login paths\\\",\\n  \\\"ref\\\": \\\"\\\"\\n}\\n\")), mdx(\"p\", null, \"The following table summarizes the object properties:\"), mdx(TableWrap, {\n    mdxType: \"TableWrap\"\n  }, mdx(\"table\", {\n    style: {\n      \"tableLayout\": \"fixed\",\n      \"width\": \"100%\"\n    }\n  }, mdx(\"thead\", null, mdx(\"tr\", null, mdx(\"th\", null, \"Property\"), mdx(\"th\", null, \"Description\"), mdx(\"th\", null, \"Constraints\"))), mdx(\"tbody\", null, mdx(\"tr\", null, mdx(\"td\", null, mdx(\"code\", null, \"id\"), mdx(\"br\", null), mdx(Type, {\n    mdxType: \"Type\"\n  }, \"String\")), mdx(\"td\", null, \"A UUIDv4 identifier generated by Cloudflare.\"), mdx(\"td\", null, mdx(\"p\", null, \"Unique, read only\"), mdx(\"p\", null, \"Length: 32 characters\"))), mdx(\"tr\", null, mdx(\"td\", null, mdx(\"code\", null, \"expression\"), mdx(\"br\", null), mdx(Type, {\n    mdxType: \"Type\"\n  }, \"String\")), mdx(\"td\", null, \"A Rules language expression used to evaluate requests. For more information, refer to \", mdx(\"a\", {\n    href: \"https://developers.cloudflare.com/ruleset-engine/rules-language/expressions\"\n  }, \"Expressions\"), \".\"), mdx(\"td\", null)), mdx(\"tr\", null, mdx(\"td\", null, mdx(\"code\", null, \"paused\"), mdx(\"br\", null), mdx(Type, {\n    mdxType: \"Type\"\n  }, \"Boolean\")), mdx(\"td\", null, \"Returns \", mdx(\"code\", {\n    className: \"InlineCode\"\n  }, \"true\"), \" when the filter is not active. Use \", mdx(\"code\", null, \"ref\"), \" to enable/disable the filter.\"), mdx(\"td\", null, \"Default: \", mdx(\"code\", {\n    className: \"InlineCode\"\n  }, \"false\"))), mdx(\"tr\", null, mdx(\"td\", null, mdx(\"code\", null, \"description\"), mdx(\"br\", null), mdx(Type, {\n    mdxType: \"Type\"\n  }, \"String\")), mdx(\"td\", null, \"An informative summary of the filter.\"), mdx(\"td\", null, \"Maximum length: 500 characters\")), mdx(\"tr\", null, mdx(\"td\", null, mdx(\"code\", null, \"ref\"), mdx(\"br\", null), mdx(Type, {\n    mdxType: \"Type\"\n  }, \"String\")), mdx(\"td\", null, \"A short string for tagging filters.\"), mdx(\"td\", null, \"Maximum length: 50 characters\"))))));\n}\n;\nMDXContent.isMDXComponent = true;","frontmatter":{"demo":null,"difficulty":null,"summary":null,"tags":null,"title":"","type":null,"updated":null}}},"pageContext":{"id":"4d75828d-266c-5f54-b891-aa02c3a0171e","fields":{"slug":"/api/cf-filters/json-object"},"frontmatter":{"title":"","type":null,"order":450,"hidden":null,"hideChildren":null,"breadcrumbs":null},"headings":[{"value":"JSON object","depth":1}],"tableOfContents":{"items":[{"url":"#json-object","title":"JSON object","items":[{"url":"#filters-object-structure-and-properties","title":"Filters object structure and properties"}]}]},"parent":{"modifiedTime":"2022-02-09","relativePath":"api/cf-filters/json-object.md"}}}