{"data":{"mdx":{"id":"581d27ba-0427-5afe-8393-54a2b0416afc","body":"var _excluded = [\"components\"];\n\nfunction _extends() { _extends = Object.assign || function (target) { for (var i = 1; i < arguments.length; i++) { var source = arguments[i]; for (var key in source) { if (Object.prototype.hasOwnProperty.call(source, key)) { target[key] = source[key]; } } } return target; }; return _extends.apply(this, arguments); }\n\nfunction _objectWithoutProperties(source, excluded) { if (source == null) return {}; var target = _objectWithoutPropertiesLoose(source, excluded); var key, i; if (Object.getOwnPropertySymbols) { var sourceSymbolKeys = Object.getOwnPropertySymbols(source); for (i = 0; i < sourceSymbolKeys.length; i++) { key = sourceSymbolKeys[i]; if (excluded.indexOf(key) >= 0) continue; if (!Object.prototype.propertyIsEnumerable.call(source, key)) continue; target[key] = source[key]; } } return target; }\n\nfunction _objectWithoutPropertiesLoose(source, excluded) { if (source == null) return {}; var target = {}; var sourceKeys = Object.keys(source); var key, i; for (i = 0; i < sourceKeys.length; i++) { key = sourceKeys[i]; if (excluded.indexOf(key) >= 0) continue; target[key] = source[key]; } return target; }\n\n/* @jsx mdx */\nvar _frontmatter = {\n  \"order\": 16,\n  \"pcx-content-type\": \"reference\"\n};\n\nvar makeShortcode = function makeShortcode(name) {\n  return function MDXDefaultShortcode(props) {\n    console.warn(\"Component \" + name + \" was not imported, exported, or provided by MDXProvider as global scope\");\n    return mdx(\"div\", props);\n  };\n};\n\nvar layoutProps = {\n  _frontmatter: _frontmatter\n};\nvar MDXLayout = \"wrapper\";\nreturn function MDXContent(_ref) {\n  var components = _ref.components,\n      props = _objectWithoutProperties(_ref, _excluded);\n\n  return mdx(MDXLayout, _extends({}, layoutProps, props, {\n    components: components,\n    mdxType: \"MDXLayout\"\n  }), mdx(\"h1\", {\n    \"id\": \"nested-structures\"\n  }, \"Nested Structures\"), mdx(\"p\", null, \"Two kinds of nested structures that behave in special ways are supported: \", mdx(\"strong\", {\n    parentName: \"p\"\n  }, \"arrays\"), \" and \", mdx(\"strong\", {\n    parentName: \"p\"\n  }, \"maps\"), \". Fields of either of these types are arrays; when they're part part of query result, which is already an array of objects, they become nested arrays.\"), mdx(\"h2\", {\n    \"id\": \"arrays\"\n  }, \"Arrays\"), mdx(\"p\", null, \"Arrays behave as a special kind of single value. There is no way to paginate through, filter, filter by, group, or group by the array.\"), mdx(\"p\", null, \"On the other hand, you can choose which fields of the underlying type you want fetched.\"), mdx(\"p\", null, \"For example, given arrays like this:\"), mdx(\"pre\", null, mdx(\"code\", {\n    parentName: \"pre\",\n    \"className\": \"language-javascript\"\n  }, \"type SubRequest {\\n    url: String!\\n    status: Int\\n}\\n\\ntype Request {\\n    date: Date!\\n    datetime: DateTime!\\n    subRequests: [SubRequest!]!\\n}\\n\")), mdx(\"p\", null, \"You can run a query to get the status by subrequest:\"), mdx(\"pre\", null, mdx(\"code\", {\n    parentName: \"pre\",\n    \"className\": \"language-javascript\"\n  }, \"{\\n    requests {\\n        date\\n        subRequests {\\n            # discard the url, only need the status\\n            status\\n        }\\n    }\\n}\\n\")), mdx(\"p\", null, \"The results would be:\"), mdx(\"pre\", null, mdx(\"code\", {\n    parentName: \"pre\",\n    \"className\": \"language-javascript\"\n  }, \"{\\n    \\\"requests\\\": [\\n        {\\n            \\\"date\\\": \\\"2018-01-01\\\",\\n            \\\"subRequests\\\": [{\\\"status\\\": 404}, {\\\"status\\\": 200}, {\\\"status\\\": 404}]\\n        },\\n        {\\n            \\\"date\\\": \\\"2018-01-01\\\",\\n            \\\"subRequests\\\": [{\\\"status\\\": 200}]\\n        }\\n    ]\\n}\\n\")), mdx(\"h2\", {\n    \"id\": \"maps\"\n  }, \"Maps\"), mdx(\"p\", null, \"Maps behave like arrays, but can be grouped using the \", mdx(\"inlineCode\", {\n    parentName: \"p\"\n  }, \"sum\"), \" function. They are used in aggregated data sets, such as \", mdx(\"inlineCode\", {\n    parentName: \"p\"\n  }, \"httpRequest1dGroups\"), \".\"), mdx(\"p\", null, \"Example maps:\"), mdx(\"pre\", null, mdx(\"code\", {\n    parentName: \"pre\",\n    \"className\": \"language-javascript\"\n  }, \"type URLStatsMapElem {\\n    url: String!\\n    requests: Int\\n    bytes: Int\\n}\\n\\ntype Request {\\n    date: Date!\\n    datetime: DateTime!\\n    urlStatsMap: [URLStatsMapElem!]!\\n}\\n\")), mdx(\"p\", null, \"Query:\"), mdx(\"pre\", null, mdx(\"code\", {\n    parentName: \"pre\",\n    \"className\": \"language-javascript\"\n  }, \"{\\n    requests {\\n        sum {\\n            urlStatsMap {\\n                url\\n                requests\\n                bytes\\n            }\\n        }\\n        dimensions {\\n            date\\n        }\\n    }\\n}\\n\")), mdx(\"p\", null, \"Response:\"), mdx(\"pre\", null, mdx(\"code\", {\n    parentName: \"pre\",\n    \"className\": \"language-javascript\"\n  }, \"{\\n    \\\"requests\\\": [\\n        {\\n            \\\"sum\\\": {\\n                \\\"urlStatsMap\\\": [\\n                    {\\n                        \\\"url\\\": \\\"hello-world.org/1\\\",\\n                        \\\"requests\\\": 123,\\n                        \\\"bytes\\\": 1024\\n                    },\\n                    {\\n                        \\\"url\\\": \\\"hello-world.org/10\\\",\\n                        \\\"requests\\\": 1230,\\n                        \\\"bytes\\\": 10240\\n                    }\\n                ]\\n            }\\n            \\\"dimensions\\\" {\\n                \\\"date\\\": \\\"2018-10-19\\\"\\n            }\\n        },\\n        ...\\n    ]\\n}\\n\")), mdx(\"h2\", {\n    \"id\": \"examples\"\n  }, \"Examples\"), mdx(\"p\", null, \"Query array fields in raw data sets:\"), mdx(\"pre\", null, mdx(\"code\", {\n    parentName: \"pre\",\n    \"className\": \"language-javascript\"\n  }, \"query NestedFields($zoneTag: string, $dateStart: string, $dateEnd: string, $datetimeStart: string, $datetimeEnd: string) {\\n      viewer {\\n        zones(filter: {zoneTag: $zoneTag}) {\\n          events(limit: 2, filter: {datetime_geq: $datetimeStart,datetime_leq: $datetimeEnd}){\\n            matches {\\n              ruleId\\n              action\\n              source\\n            }\\n          }\\n        }\\n      }\\n}\\n\")), mdx(\"p\", null, \"Example response:\"), mdx(\"pre\", null, mdx(\"code\", {\n    parentName: \"pre\",\n    \"className\": \"language-javascript\"\n  }, \"{\\n  \\\"data\\\": {\\n    \\\"viewer\\\": {\\n      \\\"zones\\\": [\\n        {\\n          \\\"events\\\": [\\n            {\\n              \\\"matches\\\": [\\n                {\\n                  \\\"action\\\": \\\"allow\\\",\\n                  \\\"ruleId\\\": \\\"rule-id-one\\\",\\n                  \\\"source\\\": \\\"asn\\\"\\n                },\\n                {\\n                  \\\"action\\\": \\\"block\\\",\\n                  \\\"ruleId\\\": \\\"rule-id-two\\\",\\n                  \\\"source\\\": \\\"asn\\\"\\n                }\\n              ]\\n            }\\n          ]\\n        }\\n      ]\\n    }\\n  },\\n  \\\"errors\\\": null\\n}\\n\")), mdx(\"p\", null, \"Query maps fields in aggregated data sets:\"), mdx(\"pre\", null, mdx(\"code\", {\n    parentName: \"pre\",\n    \"className\": \"language-javascript\"\n  }, \"query MapCapacity($zoneTag: string, $dateStart: string, $dateEnd: string, $datetimeStart: string, $datetimeEnd: string) {\\n    viewer {\\n        zones(filter: {zoneTag: $zoneTag}) {\\n            httpRequests1mGroups(\\n                limit: 10,\\n                filter: {date_geq: $dateStart, date_leq: $dateEnd, datetime_geq: $datetimeStart, datetime_lt: $datetimeEnd}) {\\n                sum {\\n                    countryMap {\\n                        clientCountryName\\n                        requests\\n                        bytes\\n                        threats\\n                    }\\n                }\\n                dimensions {\\n                    datetimeHour\\n                }\\n            }\\n        }\\n    }\\n}\\n\")), mdx(\"p\", null, \"Example response:\"), mdx(\"pre\", null, mdx(\"code\", {\n    parentName: \"pre\",\n    \"className\": \"language-javascript\"\n  }, \"{\\n  \\\"data\\\": {\\n    \\\"viewer\\\": {\\n      \\\"zones\\\": [\\n        {\\n          \\\"httpRequests1mGroups\\\": [\\n            {\\n              \\\"dimensions\\\": {\\n                \\\"datetime\\\": \\\"2019-03-08T17:00:00Z\\\"\\n              },\\n              \\\"sum\\\": {\\n                \\\"countryMap\\\": [\\n                  {\\n                    \\\"bytes\\\": 51911317,\\n                    \\\"clientCountryName\\\": \\\"XK\\\",\\n                    \\\"requests\\\": 4492,\\n                    \\\"threats\\\": 0\\n                  },\\n                  {\\n                    \\\"bytes\\\": 1816103586,\\n                    \\\"clientCountryName\\\": \\\"T1\\\",\\n                    \\\"requests\\\": 132423,\\n                    \\\"threats\\\": 0\\n                  },\\n                  ...\\n                ]\\n              }\\n            }\\n          ]\\n        }\\n      ]\\n    }\\n  },\\n  \\\"errors\\\": null\\n}\\n\")));\n}\n;\nMDXContent.isMDXComponent = true;","frontmatter":{"demo":null,"difficulty":null,"summary":null,"tags":null,"title":"","type":null,"updated":null}}},"pageContext":{"id":"581d27ba-0427-5afe-8393-54a2b0416afc","fields":{"slug":"/graphql-api/features/nested-structures"},"frontmatter":{"title":"","type":null,"order":16,"hidden":null,"hideChildren":null,"breadcrumbs":null},"headings":[{"value":"Nested Structures","depth":1}],"tableOfContents":{"items":[{"url":"#nested-structures","title":"Nested Structures","items":[{"url":"#arrays","title":"Arrays"},{"url":"#maps","title":"Maps"},{"url":"#examples","title":"Examples"}]}]},"parent":{"modifiedTime":"2021-10-26","relativePath":"graphql-api/features/nested-structures/index.md"}}}